fractalantennaarrayfactor/__init__.py
fractalantenna-0.1.dist-info/LICENSE.txt
fractalantenna-0.1.dist-info/METADATA
fractalantenna-0.1.dist-info/WHEEL
fractalantenna-0.1.dist-info/top_level.txt
fractalantenna-0.1.dist-info/RECORD
