Metadata-Version: 2.1
Name: fractalantenna
Version: 0.1
Summary: array factor code for fractal antenna
Home-page: UNKNOWN
Author: Kadupu Sai Chandana
Author-email: saichandana2817@gmail.com
License: UNKNOWN
Platform: UNKNOWN
Classifier: Programming Language :: Python :: 3
Classifier: License :: OSI Approved :: MIT License
Classifier: Operating System :: OS Independent
License-File: LICENSE.txt
